MANIFEST.in
README.rst
setup.cfg
setup.py
linked_list/__init__.py
linked_list/base.py
linked_list/dll.py
linked_list/ll.py
linked_list/tools.py
linked_list.egg-info/PKG-INFO
linked_list.egg-info/SOURCES.txt
linked_list.egg-info/dependency_links.txt
linked_list.egg-info/not-zip-safe
linked_list.egg-info/top_level.txt