Metadata-Version: 1.1
Name: linked-list
Version: 0.0.4
Summary: Classes for linked lists and doubly linked lists
Home-page: https://github.com/jakab922/linked_list
Author: Daniel Papp
Author-email: jakab922@gmail.com
License: MIT
Download-URL: https://github.com/jakab922/linked_list/tarball/0.0.4
Keywords: linked list data structure
Platform: UNKNOWN
Classifier: Development Status :: 3 - Alpha
Classifier: License :: OSI Approved :: MIT License
Classifier: Programming Language :: Python :: 2.7
